naposapi/__init__.py
naposapi-0.1.dist-info/DESCRIPTION.rst
naposapi-0.1.dist-info/METADATA
naposapi-0.1.dist-info/RECORD
naposapi-0.1.dist-info/WHEEL
naposapi-0.1.dist-info/metadata.json
naposapi-0.1.dist-info/top_level.txt
